AMS_C35_SPI/il2244_spi.v
`ifndef IL2244_SPI_V
`define IL2244_SPI_V
	
	// MODE 0 SPI Slave V2.1
	// Author: Saul Rodriguez
	// Date: 2026-03-06

	// NOTE: This version implements an asynchronous SPI slave block for the IL2244 ASIC
	// Usage:
	
	// Async resetn (L) will reset the module. Once SPI_CS goes (L) the module will receive and transmit bits through the SPI_MOSI and 
	// SPI_MISO lines. The configuration word is composed of 40 bits (5 bytes) which are divided in two digital words: 
	// adress (1 byte) and data (4 bytes). Accordingly, the complete configuration word is:
	// | 8-bit address | 32-bit data |
	// Once 40 bits have been received at the SPI_MOSI line, the configuration registers (32 bits)
	// conf0, conf1 are updated
	// 
	// The 2 LSB of the 8-bit address define the configration register that is updated:
	// address[1:0] == 00 => conf0
	// address[1:0] == 01 => conf1
	  

	module il2244_spi (			
		input resetn, // Reset async. (L)
		input SPI_CS, // chip select  (L)
		input SPI_Clk, // Mode 0, data is sampled at the rising edge
		input SPI_MOSI, // Master output  Slave Input				
		output reg [31:0] conf0,
		output reg [31:0] conf1 );
		
	/******************************************************/
    /* Recover the SPI_MOSI data only when SPI_CS is (L)  */
	/******************************************************/
		
		reg [39:0] Rx_data_temp;
				
		always @(posedge SPI_Clk or negedge resetn) begin
			if (resetn == 1'b0) begin
				//Rx_count <= 5'b0_0000;
                Rx_data_temp <= 0;				
			end else begin
                if (SPI_CS == 1'b0) begin                   
                    Rx_data_temp <= {Rx_data_temp[38:0],SPI_MOSI};	                                        
                end
			end		
		end

    /****************************************************************/
    /* Count the number of bits being received while SPI_CS is (L)  */
	/****************************************************************/

        reg [5:0] Rx_count;
        always @(posedge SPI_Clk or posedge SPI_CS) begin
			if (SPI_CS == 1'b1) begin
				Rx_count <= 5'b0_0000;                
			end else begin
                Rx_count <= Rx_count + 1;
			end		
		end

    /*********************************************/
    /* Copy the temp data to the output registers */
    /*********************************************/
		
        wire [1:0]addr;
		assign addr = Rx_data_temp[33:32];        
		
        always @(posedge SPI_CS or negedge resetn) begin
            if (resetn == 1'b0) begin
				conf0 <= 0;
				conf1 <= 0;				
            end else begin
                // Copy data only if 40 bits (5 bytes) have been completely received                
				if (Rx_count == 40) begin 
					case (addr)
						2'b00 : conf0 <= Rx_data_temp[31:0];
						2'b01 : conf1 <= Rx_data_temp[31:0];						
					endcase                                                      
                end                
            end
        end

	endmodule
		
`endif

AMS_C35_SPI/il2244_dig.v
`ifndef IL2244_DIG_V
`define IL2244_DIG_V

`include "il2244_spi.v"

module il2244_dig (
			input reset_l, // Reset async. (L)
            input porborn, //Power-on-Reset/Brown-out-Reset (L)
			input SPI_CS, // chip select  (L)
			input SPI_Clk, // Mode 0, data is sampled at the rising edge
			input SPI_MOSI, // Master output  Slave Input		
			output [2:0] fECG_filter,  // control fECG GMC filter bandwidth
            output [2:0] fECG_gain, // Controls the fECG variable gain
            output fECG_BG_sel, // Control fECG selection of external/internal bandgap
            output [5:0] potentiostat, // Copntrols the gain of the potentiostat
            output [2:0] ECG_filter,  // control ECG GMC filter bandwidth
            output [3:0] ECG_gain, // Controls the fECG variable gain
            output ECG_BG_sel // Control the ECG selection of external/internal bandgap
            ); 
 

    /**********************************************/
    /* Configuration words bit mapping            */
    /*                                            */
    /* conf0:                                     */
    /*                                            */
    /* bits 2-0: [2:0] fECG_filter                */
    /* bits 5-3: [2:0] fECG_gain                  */
    /* bits 6:   fECG_BG_sel                      */
    /* bits 12-7:  [5:0] potentiostat                    */
    /*                                            */
    /* conf1:                                     */
    /*                                            */
    /* bits 9-0: [9:0] ramp_factor                */
    /* bits 19-10: [9:0] OFF_time                 */
    /* bit 22: enable                             */
    /* bits 23-21: [2:0] phaseDuration            */
    /*                                            */
    /**********************************************/

    wire resetn;

    wire [31:0] conf0;
	wire [31:0] conf1;

    assign resetn = reset_l & porborn;

    il2244_spi spi (
        .resetn(resetn),
        .SPI_CS(SPI_CS),
        .SPI_Clk(SPI_Clk),
        .SPI_MOSI(SPI_MOSI),
        .conf0(conf0),
        .conf1(conf1)
    );

    // Map conf0 to the respective outputs
    assign fECG_filter = conf0[2:0];
    assign fECG_gain = conf0[5:3];
    assign fECG_BG_sel = conf0[6];
    assign potentiostat = conf0[12:7];

    // Map conf1 to the respective outputs
    assign ECG_filter = conf1[2:0]; // Assuming bits 2-0 for ECG_filter
    assign ECG_gain = conf1[6:3];   // Assuming bits 6-3 for ECG_gain
    assign ECG_BG_sel = conf1[7];   // Assuming bit 7 for ECG_BG_sel

endmodule

`endif

AMS_C35_SPI/il2244_dig_tb.v
`include "il2244_dig.v"

`timescale 1us/ 1ps

module DIG_stimulus(
    output reg SPI_Clk,
	output reg SPI_MOSI,
	output reg SPI_CS,
	output reg reset_l,	
	output reg porborn);

	parameter SPI_CLK_DELAY = 1; // 500 kHz

    reg [7:0] TX_data; // Data to send through MOSI	
	

	// Received signals
	
	wire [2:0] fECG_filter;  // control fECG GMC filter bandwidth
    wire [2:0] fECG_gain; // Controls the fECG variable gain
    wire fECG_BG_sel; // Control fECG selection of external/internal bandgap
    wire [5:0] potentiostat; // Copntrols the gain of the potentiostat
    wire [2:0] ECG_filter;  // control ECG GMC filter bandwidth
    wire [3:0] ECG_gain; // Controls the fECG variable gain
    wire ECG_BG_sel; // Control the ECG selection of external/internal bandgap

	il2244_dig dut (
		.reset_l(reset_l),
		.porborn(porborn),	
		.SPI_CS(SPI_CS),
		.SPI_Clk(SPI_Clk),
		.SPI_MOSI(SPI_MOSI),
		.fECG_filter(fECG_filter),
		.fECG_gain(fECG_gain),	
		.fECG_BG_sel(fECG_BG_sel),
		.potentiostat(potentiostat),
		.ECG_filter(ECG_filter),
		.ECG_gain(ECG_gain),
		.ECG_BG_sel(ECG_BG_sel)
	);
	 

    initial begin
        // Required for EDA Playground
		$dumpfile("dump.vcd"); 
		$dumpvars;
		$display("******************************************");
		$display("Test ASKA SPI Slave");

		porborn = 1'b1; // Power-on-Reset/Brown-out-Reset (L)
        TX_data = 8'h00;
		reset_l = 1'b1;		
		SPI_CS = 1'b1;
		SPI_Clk = 1'b0;
		SPI_MOSI = 1'b0;

        //Reset
		#(10*SPI_CLK_DELAY) reset_l = 1'b0;
		#(10*SPI_CLK_DELAY) reset_l = 1'b1;
		#(10*SPI_CLK_DELAY);

		// Change conf0
        send_SPI(8'h00,32'haabbccdd);

		// Change conf1
        send_SPI(8'h01,32'hccaaeeff);

		// Send wrong address
        send_SPI(8'h02,32'h55aadd22);

		// Send wrong number of bytes
        send_SPI_error(8'h01,32'h11223344);

		// Change conf0 again
        send_SPI(8'h00,32'hbbeeccaa);

        #(100*SPI_CLK_DELAY); 
		$display("******************************************");		
		$finish;

        
    end

	reg[8*6:1] str1;

    task send_SPI(input [7:0] add, input [31:0] data);
		begin
			SPI_CS = 1'b0;
			#(4*SPI_CLK_DELAY); // models delay between CS and SPI master data
			
			send_byte(add);
			send_byte(data[31:24]);
			send_byte(data[23:16]);
			send_byte(data[15:8]);
			send_byte(data[7:0]);
			
			#(4*SPI_CLK_DELAY); // models delay between CS and SPI master 
			SPI_CS = 1'b1;	
			
			//Check values
			#(4*SPI_CLK_DELAY);

			$display("sent SPI add 0x%X, data 0x%X at time:",add, data, $time);
/*			
			case (add)
				8'h00:  	begin
								str1 = (data == conf0)? "OK" : "ERROR";
								$display("sent conf0 0x%X, register conf0 0x%X, %s", data, conf0, str1);
							end
				8'h01: 		begin
								str1 = (data == conf1)? "OK" : "ERROR";
								$display("sent conf1 0x%X, register conf0 0x%X, %s", data, conf1, str1);
							end
				default:	begin
								$display(" 					ERROR WRONG ADDRESS");
							end

			endcase

			$display("conf0 = 0x%X ",conf0);
			$display("conf1 = 0x%X ",conf1);
*/
			
		end
	endtask
	
	// This function sends an incomplete word of 32 bits instead of 40
	task send_SPI_error(input [7:0] add, input [31:0] data);
		begin
			$display("ERROR TEST: SENDING INCOMPLETE WORD");
			SPI_CS = 1'b0;
			#(4*SPI_CLK_DELAY); // models delay between CS and SPI master data
			
			send_byte(add);
			send_byte(data[31:24]);
			send_byte(data[23:16]);
			//send_byte(data[15:8]);
			send_byte(data[7:0]);
			
			#(4*SPI_CLK_DELAY); // models delay between CS and SPI master 
			SPI_CS = 1'b1;	
			
			//Check values
			#(4*SPI_CLK_DELAY);

			$display("sent SPI add 0x%X, data 0x%X at time:",add, data, $time);
			
			/*

			case (add)
				8'h00:  	begin
								str1 = (data == conf0)? "OK" : "ERROR";
								$display("sent conf0 0x%X, register conf0 0x%X, %s", data, conf0, str1);
							end
				8'h01: 		begin
								str1 = (data == conf1)? "OK" : "ERROR";
								$display("sent conf1 0x%X, register conf0 0x%X, %s", data, conf1, str1);
							end
				default:	begin
								$display("Wrong address, 					ERROR");
							end

			endcase

			$display("conf0 = 0x%X ",conf0);
			$display("conf1 = 0x%X ",conf1);

			*/			
		end
	endtask

    task send_byte(input [7:0] data);
		begin
			TX_data = data;			

			SPI_Clk = 1'b0;
			SPI_MOSI = TX_data[7];
						
			#SPI_CLK_DELAY;		
			SPI_Clk = 1'b1;
			#SPI_CLK_DELAY;
			SPI_Clk = 1'b0;
			SPI_MOSI = TX_data[6];
		
			#SPI_CLK_DELAY;
			SPI_Clk = 1'b1;			
			#SPI_CLK_DELAY;
			SPI_Clk = 1'b0;
			SPI_MOSI = TX_data[5];
				
			#SPI_CLK_DELAY;
			SPI_Clk = 1'b1;
			#SPI_CLK_DELAY;
			SPI_Clk = 1'b0;
			SPI_MOSI = TX_data[4];

			#SPI_CLK_DELAY;
			SPI_Clk = 1'b1;
			#SPI_CLK_DELAY;
			SPI_Clk = 1'b0;
			SPI_MOSI = TX_data[3];
		
			#SPI_CLK_DELAY;
			SPI_Clk = 1'b1;			
			#SPI_CLK_DELAY;
			SPI_Clk = 1'b0;
			SPI_MOSI = TX_data[2];

			#SPI_CLK_DELAY;
			SPI_Clk = 1'b1;			
			#SPI_CLK_DELAY;
			SPI_Clk = 1'b0;
			SPI_MOSI = TX_data[1];

			#SPI_CLK_DELAY;
			SPI_Clk = 1'b1;			
			#SPI_CLK_DELAY;
			SPI_Clk = 1'b0;
			SPI_MOSI = TX_data[0];
		
			#SPI_CLK_DELAY;
			SPI_Clk = 1'b1;
			
			#SPI_CLK_DELAY;
			SPI_Clk = 1'b0;
						
		end
	endtask

endmodule

AMS_C35_SPI/dump.vcd
$date
	Mon May 11 16:15:06 2026
$end
$version
	Icarus Verilog
$end
$timescale
	1ps
$end
$scope module DIG_stimulus $end
$var wire 6 ! potentiostat [5:0] $end
$var wire 3 " fECG_gain [2:0] $end
$var wire 3 # fECG_filter [2:0] $end
$var wire 1 $ fECG_BG_sel $end
$var wire 4 % ECG_gain [3:0] $end
$var wire 3 & ECG_filter [2:0] $end
$var wire 1 ' ECG_BG_sel $end
$var parameter 32 ( SPI_CLK_DELAY $end
$var reg 1 ) SPI_CS $end
$var reg 1 * SPI_Clk $end
$var reg 1 + SPI_MOSI $end
$var reg 8 , TX_data [7:0] $end
$var reg 1 - porborn $end
$var reg 1 . reset_l $end
$scope module dut $end
$var wire 1 ) SPI_CS $end
$var wire 1 * SPI_Clk $end
$var wire 1 + SPI_MOSI $end
$var wire 1 - porborn $end
$var wire 1 . reset_l $end
$var wire 1 / resetn $end
$var wire 6 0 potentiostat [5:0] $end
$var wire 3 1 fECG_gain [2:0] $end
$var wire 3 2 fECG_filter [2:0] $end
$var wire 1 $ fECG_BG_sel $end
$var wire 32 3 conf1 [31:0] $end
$var wire 32 4 conf0 [31:0] $end
$var wire 4 5 ECG_gain [3:0] $end
$var wire 3 6 ECG_filter [2:0] $end
$var wire 1 ' ECG_BG_sel $end
$scope module spi $end
$var wire 1 ) SPI_CS $end
$var wire 1 * SPI_Clk $end
$var wire 1 + SPI_MOSI $end
$var wire 1 / resetn $end
$var wire 2 7 addr [1:0] $end
$var reg 6 8 Rx_count [5:0] $end
$var reg 40 9 Rx_data_temp [39:0] $end
$var reg 32 : conf0 [31:0] $end
$var reg 32 ; conf1 [31:0] $end
$upscope $end
$upscope $end
$scope task send_SPI $end
$var reg 8 < add [7:0] $end
$var reg 32 = data [31:0] $end
$upscope $end
$scope task send_SPI_error $end
$var reg 8 > add [7:0] $end
$var reg 32 ? data [31:0] $end
$upscope $end
$scope task send_byte $end
$var reg 8 @ data [7:0] $end
$upscope $end
$upscope $end
$enddefinitions $end
$comment Show the parameter values. $end
$dumpall
b1 (
$end
#0
$dumpvars
bx @
bx ?
bx >
bx =
bx <
bx ;
bx :
bx 9
b0 8
bx 7
bx 6
bx 5
bx 4
bx 3
bx 2
bx 1
bx 0
1/
1.
1-
b0 ,
0+
0*
1)
x'
bx &
bx %
x$
bx #
bx "
bx !
$end
#10000000
0'
b0 %
b0 5
b0 &
b0 6
b0 !
b0 0
0$
b0 "
b0 1
b0 #
b0 2
b0 7
b0 3
b0 ;
b0 4
b0 :
b0 9
0/
0.
#20000000
1/
1.
#30000000
0)
b10101010101110111100110011011101 =
b0 <
#34000000
b0 @
#35000000
b1 8
1*
#36000000
0*
#37000000
b10 8
1*
#38000000
0*
#39000000
b11 8
1*
#40000000
0*
#41000000
b100 8
1*
#42000000
0*
#43000000
b101 8
1*
#44000000
0*
#45000000
b110 8
1*
#46000000
0*
#47000000
b111 8
1*
#48000000
0*
#49000000
b1000 8
1*
#50000000
1+
b10101010 ,
b10101010 @
0*
#51000000
b1001 8
b1 9
1*
#52000000
0+
0*
#53000000
b1010 8
b10 9
1*
#54000000
1+
0*
#55000000
b1011 8
b101 9
1*
#56000000
0+
0*
#57000000
b1100 8
b1010 9
1*
#58000000
1+
0*
#59000000
b1101 8
b10101 9
1*
#60000000
0+
0*
#61000000
b1110 8
b101010 9
1*
#62000000
1+
0*
#63000000
b1111 8
b1010101 9
1*
#64000000
0+
0*
#65000000
b10000 8
b10101010 9
1*
#66000000
1+
b10111011 ,
b10111011 @
0*
#67000000
b10001 8
b101010101 9
1*
#68000000
0+
0*
#69000000
b10010 8
b1010101010 9
1*
#70000000
1+
0*
#71000000
b10011 8
b10101010101 9
1*
#72000000
0*
#73000000
b10100 8
b101010101011 9
1*
#74000000
0*
#75000000
b10101 8
b1010101010111 9
1*
#76000000
0+
0*
#77000000
b10110 8
b10101010101110 9
1*
#78000000
1+
0*
#79000000
b10111 8
b101010101011101 9
1*
#80000000
0*
#81000000
b11000 8
b1010101010111011 9
1*
#82000000
b11001100 ,
b11001100 @
0*
#83000000
b11001 8
b10101010101110111 9
1*
#84000000
0*
#85000000
b11010 8
b101010101011101111 9
1*
#86000000
0+
0*
#87000000
b11011 8
b1010101010111011110 9
1*
#88000000
0*
#89000000
b11100 8
b10101010101110111100 9
1*
#90000000
1+
0*
#91000000
b11101 8
b101010101011101111001 9
1*
#92000000
0*
#93000000
b11110 8
b1010101010111011110011 9
1*
#94000000
0+
0*
#95000000
b11111 8
b10101010101110111100110 9
1*
#96000000
0*
#97000000
b100000 8
b101010101011101111001100 9
1*
#98000000
1+
b11011101 ,
b11011101 @
0*
#99000000
b100001 8
b1010101010111011110011001 9
1*
#100000000
0*
#101000000
b100010 8
b10101010101110111100110011 9
1*
#102000000
0+
0*
#103000000
b100011 8
b101010101011101111001100110 9
1*
#104000000
1+
0*
#105000000
b100100 8
b1010101010111011110011001101 9
1*
#106000000
0*
#107000000
b100101 8
b10101010101110111100110011011 9
1*
#108000000
0*
#109000000
b100110 8
b101010101011101111001100110111 9
1*
#110000000
0+
0*
#111000000
b100111 8
b1010101010111011110011001101110 9
1*
#112000000
1+
0*
#113000000
b101000 8
b10101010101110111100110011011101 9
1*
#114000000
0*
#118000000
b11001 !
b11001 0
1$
b11 "
b11 1
b101 #
b101 2
b10101010101110111100110011011101 4
b10101010101110111100110011011101 :
b0 8
1)
#122000000
0)
b11001100101010101110111011111111 =
b1 <
#126000000
0+
b1 ,
b1 @
#127000000
b1 7
b1 8
b101010101011101111001100110111010 9
1*
#128000000
0*
#129000000
b10 7
b10 8
b1010101010111011110011001101110100 9
1*
#130000000
0*
#131000000
b1 7
b11 8
b10101010101110111100110011011101000 9
1*
#132000000
0*
#133000000
b10 7
b100 8
b101010101011101111001100110111010000 9
1*
#134000000
0*
#135000000
b1 7
b101 8
b1010101010111011110011001101110100000 9
1*
#136000000
0*
#137000000
b10 7
b110 8
b10101010101110111100110011011101000000 9
1*
#138000000
0*
#139000000
b1 7
b111 8
b101010101011101111001100110111010000000 9
1*
#140000000
1+
0*
#141000000
b10 7
b1000 8
b1010101010111011110011001101110100000001 9
1*
#142000000
b11001100 ,
b11001100 @
0*
#143000000
b1 7
b1001 8
b101010101110111100110011011101000000011 9
1*
#144000000
0*
#145000000
b10 7
b1010 8
b1010101011101111001100110111010000000111 9
1*
#146000000
0+
0*
#147000000
b1 7
b1011 8
b101010111011110011001101110100000001110 9
1*
#148000000
0*
#149000000
b11 7
b1100 8
b1010101110111100110011011101000000011100 9
1*
#150000000
1+
0*
#151000000
b1101 8
b101011101111001100110111010000000111001 9
1*
#152000000
0*
#153000000
b10 7
b1110 8
b1010111011110011001101110100000001110011 9
1*
#154000000
0+
0*
#155000000
b1 7
b1111 8
b101110111100110011011101000000011100110 9
1*
#156000000
0*
#157000000
b11 7
b10000 8
b1011101111001100110111010000000111001100 9
1*
#158000000
1+
b10101010 ,
b10101010 @
0*
#159000000
b10001 8
b111011110011001101110100000001110011001 9
1*
#160000000
0+
0*
#161000000
b10010 8
b1110111100110011011101000000011100110010 9
1*
#162000000
1+
0*
#163000000
b10 7
b10011 8
b1101111001100110111010000000111001100101 9
1*
#164000000
0+
0*
#165000000
b0 7
b10100 8
b1011110011001101110100000001110011001010 9
1*
#166000000
1+
0*
#167000000
b1 7
b10101 8
b111100110011011101000000011100110010101 9
1*
#168000000
0+
0*
#169000000
b11 7
b10110 8
b1111001100110111010000000111001100101010 9
1*
#170000000
1+
0*
#171000000
b10 7
b10111 8
b1110011001101110100000001110011001010101 9
1*
#172000000
0+
0*
#173000000
b0 7
b11000 8
b1100110011011101000000011100110010101010 9
1*
#174000000
1+
b11101110 ,
b11101110 @
0*
#175000000
b1 7
b11001 8
b1001100110111010000000111001100101010101 9
1*
#176000000
0*
#177000000
b11 7
b11010 8
b11001101110100000001110011001010101011 9
1*
#178000000
0*
#179000000
b10 7
b11011 8
b110011011101000000011100110010101010111 9
1*
#180000000
0+
0*
#181000000
b1 7
b11100 8
b1100110111010000000111001100101010101110 9
1*
#182000000
1+
0*
#183000000
b11 7
b11101 8
b1001101110100000001110011001010101011101 9
1*
#184000000
0*
#185000000
b11110 8
b11011101000000011100110010101010111011 9
1*
#186000000
0*
#187000000
b10 7
b11111 8
b110111010000000111001100101010101110111 9
1*
#188000000
0+
0*
#189000000
b1 7
b100000 8
b1101110100000001110011001010101011101110 9
1*
#190000000
1+
b11111111 ,
b11111111 @
0*
#191000000
b10 7
b100001 8
b1011101000000011100110010101010111011101 9
1*
#192000000
0*
#193000000
b0 7
b100010 8
b111010000000111001100101010101110111011 9
1*
#194000000
0*
#195000000
b100011 8
b1110100000001110011001010101011101110111 9
1*
#196000000
0*
#197000000
b100100 8
b1101000000011100110010101010111011101111 9
1*
#198000000
0*
#199000000
b100101 8
b1010000000111001100101010101110111011111 9
1*
#200000000
0*
#201000000
b100110 8
b100000001110011001010101011101110111111 9
1*
#202000000
0*
#203000000
b100111 8
b1000000011100110010101010111011101111111 9
1*
#204000000
0*
#205000000
b1 7
b101000 8
b111001100101010101110111011111111 9
1*
#206000000
0*
#210000000
1'
b1111 %
b1111 5
b111 &
b111 6
b11001100101010101110111011111111 3
b11001100101010101110111011111111 ;
b0 8
1)
#214000000
0)
b1010101101010101101110100100010 =
b10 <
#218000000
0+
b10 ,
b10 @
#219000000
b11 7
b1 8
b1110011001010101011101110111111110 9
1*
#220000000
0*
#221000000
b10 8
b11100110010101010111011101111111100 9
1*
#222000000
0*
#223000000
b10 7
b11 8
b111001100101010101110111011111111000 9
1*
#224000000
0*
#225000000
b0 7
b100 8
b1110011001010101011101110111111110000 9
1*
#226000000
0*
#227000000
b1 7
b101 8
b11100110010101010111011101111111100000 9
1*
#228000000
0*
#229000000
b11 7
b110 8
b111001100101010101110111011111111000000 9
1*
#230000000
1+
0*
#231000000
b10 7
b111 8
b1110011001010101011101110111111110000001 9
1*
#232000000
0+
0*
#233000000
b0 7
b1000 8
b1100110010101010111011101111111100000010 9
1*
#234000000
b1010101 ,
b1010101 @
0*
#235000000
b1 7
b1001 8
b1001100101010101110111011111111000000100 9
1*
#236000000
1+
0*
#237000000
b10 7
b1010 8
b11001010101011101110111111110000001001 9
1*
#238000000
0+
0*
#239000000
b1 7
b1011 8
b110010101010111011101111111100000010010 9
1*
#240000000
1+
0*
#241000000
b10 7
b1100 8
b1100101010101110111011111111000000100101 9
1*
#242000000
0+
0*
#243000000
b1 7
b1101 8
b1001010101011101110111111110000001001010 9
1*
#244000000
1+
0*
#245000000
b10 7
b1110 8
b10101010111011101111111100000010010101 9
1*
#246000000
0+
0*
#247000000
b1 7
b1111 8
b101010101110111011111111000000100101010 9
1*
#248000000
1+
0*
#249000000
b10 7
b10000 8
b1010101011101110111111110000001001010101 9
1*
#250000000
b10101010 ,
b10101010 @
0*
#251000000
b1 7
b10001 8
b101010111011101111111100000010010101011 9
1*
#252000000
0+
0*
#253000000
b11 7
b10010 8
b1010101110111011111111000000100101010110 9
1*
#254000000
1+
0*
#255000000
b10011 8
b101011101110111111110000001001010101101 9
1*
#256000000
0+
0*
#257000000
b10 7
b10100 8
b1010111011101111111100000010010101011010 9
1*
#258000000
1+
0*
#259000000
b1 7
b10101 8
b101110111011111111000000100101010110101 9
1*
#260000000
0+
0*
#261000000
b11 7
b10110 8
b1011101110111111110000001001010101101010 9
1*
#262000000
1+
0*
#263000000
b10111 8
b111011101111111100000010010101011010101 9
1*
#264000000
0+
0*
#265000000
b10 7
b11000 8
b1110111011111111000000100101010110101010 9
1*
#266000000
1+
b11011101 ,
b11011101 @
0*
#267000000
b1 7
b11001 8
b1101110111111110000001001010101101010101 9
1*
#268000000
0*
#269000000
b11 7
b11010 8
b1011101111111100000010010101011010101011 9
1*
#270000000
0+
0*
#271000000
b11011 8
b111011111111000000100101010110101010110 9
1*
#272000000
1+
0*
#273000000
b11100 8
b1110111111110000001001010101101010101101 9
1*
#274000000
0*
#275000000
b11101 8
b1101111111100000010010101011010101011011 9
1*
#276000000
0*
#277000000
b11110 8
b1011111111000000100101010110101010110111 9
1*
#278000000
0+
0*
#279000000
b11111 8
b111111110000001001010101101010101101110 9
1*
#280000000
1+
0*
#281000000
b100000 8
b1111111100000010010101011010101011011101 9
1*
#282000000
0+
b100010 ,
b100010 @
0*
#283000000
b10 7
b100001 8
b1111111000000100101010110101010110111010 9
1*
#284000000
0*
#285000000
b0 7
b100010 8
b1111110000001001010101101010101101110100 9
1*
#286000000
1+
0*
#287000000
b100011 8
b1111100000010010101011010101011011101001 9
1*
#288000000
0+
0*
#289000000
b100100 8
b1111000000100101010110101010110111010010 9
1*
#290000000
0*
#291000000
b100101 8
b1110000001001010101101010101101110100100 9
1*
#292000000
0*
#293000000
b100110 8
b1100000010010101011010101011011101001000 9
1*
#294000000
1+
0*
#295000000
b1 7
b100111 8
b1000000100101010110101010110111010010001 9
1*
#296000000
0+
0*
#297000000
b10 7
b101000 8
b1001010101101010101101110100100010 9
1*
#298000000
0*
#302000000
b0 8
1)
#306000000
0)
b10001001000100011001101000100 ?
b1 >
#310000000
b1 ,
b1 @
#311000000
b0 7
b1 8
b10010101011010101011011101001000100 9
1*
#312000000
0*
#313000000
b1 7
b10 8
b100101010110101010110111010010001000 9
1*
#314000000
0*
#315000000
b10 7
b11 8
b1001010101101010101101110100100010000 9
1*
#316000000
0*
#317000000
b1 7
b100 8
b10010101011010101011011101001000100000 9
1*
#318000000
0*
#319000000
b10 7
b101 8
b100101010110101010110111010010001000000 9
1*
#320000000
0*
#321000000
b1 7
b110 8
b1001010101101010101101110100100010000000 9
1*
#322000000
0*
#323000000
b10 7
b111 8
b10101011010101011011101001000100000000 9
1*
#324000000
1+
0*
#325000000
b1 7
b1000 8
b101010110101010110111010010001000000001 9
1*
#326000000
0+
b10001 ,
b10001 @
0*
#327000000
b11 7
b1001 8
b1010101101010101101110100100010000000010 9
1*
#328000000
0*
#329000000
b10 7
b1010 8
b101011010101011011101001000100000000100 9
1*
#330000000
0*
#331000000
b1 7
b1011 8
b1010110101010110111010010001000000001000 9
1*
#332000000
1+
0*
#333000000
b10 7
b1100 8
b101101010101101110100100010000000010001 9
1*
#334000000
0+
0*
#335000000
b1 7
b1101 8
b1011010101011011101001000100000000100010 9
1*
#336000000
0*
#337000000
b10 7
b1110 8
b110101010110111010010001000000001000100 9
1*
#338000000
0*
#339000000
b1 7
b1111 8
b1101010101101110100100010000000010001000 9
1*
#340000000
1+
0*
#341000000
b10 7
b10000 8
b1010101011011101001000100000000100010001 9
1*
#342000000
0+
b100010 ,
b100010 @
0*
#343000000
b1 7
b10001 8
b101010110111010010001000000001000100010 9
1*
#344000000
0*
#345000000
b11 7
b10010 8
b1010101101110100100010000000010001000100 9
1*
#346000000
1+
0*
#347000000
b10 7
b10011 8
b101011011101001000100000000100010001001 9
1*
#348000000
0+
0*
#349000000
b1 7
b10100 8
b1010110111010010001000000001000100010010 9
1*
#350000000
0*
#351000000
b11 7
b10101 8
b101101110100100010000000010001000100100 9
1*
#352000000
0*
#353000000
b10110 8
b1011011101001000100000000100010001001000 9
1*
#354000000
1+
0*
#355000000
b10 7
b10111 8
b110111010010001000000001000100010010001 9
1*
#356000000
0+
0*
#357000000
b1 7
b11000 8
b1101110100100010000000010001000100100010 9
1*
#358000000
b1000100 ,
b1000100 @
0*
#359000000
b10 7
b11001 8
b1011101001000100000000100010001001000100 9
1*
#360000000
1+
0*
#361000000
b0 7
b11010 8
b111010010001000000001000100010010001001 9
1*
#362000000
0+
0*
#363000000
b1 7
b11011 8
b1110100100010000000010001000100100010010 9
1*
#364000000
0*
#365000000
b10 7
b11100 8
b1101001000100000000100010001001000100100 9
1*
#366000000
0*
#367000000
b0 7
b11101 8
b1010010001000000001000100010010001001000 9
1*
#368000000
1+
0*
#369000000
b11110 8
b100100010000000010001000100100010010001 9
1*
#370000000
0+
0*
#371000000
b1 7
b11111 8
b1001000100000000100010001001000100100010 9
1*
#372000000
0*
#373000000
b10 7
b100000 8
b10001000000001000100010010001001000100 9
1*
#374000000
0*
#378000000
b0 8
1)
#382000000
0)
b10111011111011101100110010101010 =
b0 <
#386000000
b0 ,
b0 @
#387000000
b0 7
b1 8
b100010000000010001000100100010010001000 9
1*
#388000000
0*
#389000000
b10 8
b1000100000000100010001001000100100010000 9
1*
#390000000
0*
#391000000
b11 8
b1000000001000100010010001001000100000 9
1*
#392000000
0*
#393000000
b100 8
b10000000010001000100100010010001000000 9
1*
#394000000
0*
#395000000
b101 8
b100000000100010001001000100100010000000 9
1*
#396000000
0*
#397000000
b110 8
b1000000001000100010010001001000100000000 9
1*
#398000000
0*
#399000000
b111 8
b10001000100100010010001000000000 9
1*
#400000000
0*
#401000000
b1 7
b1000 8
b100010001001000100100010000000000 9
1*
#402000000
1+
b10111011 ,
b10111011 @
0*
#403000000
b10 7
b1001 8
b1000100010010001001000100000000001 9
1*
#404000000
0+
0*
#405000000
b0 7
b1010 8
b10001000100100010010001000000000010 9
1*
#406000000
1+
0*
#407000000
b1011 8
b100010001001000100100010000000000101 9
1*
#408000000
0*
#409000000
b1 7
b1100 8
b1000100010010001001000100000000001011 9
1*
#410000000
0*
#411000000
b10 7
b1101 8
b10001000100100010010001000000000010111 9
1*
#412000000
0+
0*
#413000000
b0 7
b1110 8
b100010001001000100100010000000000101110 9
1*
#414000000
1+
0*
#415000000
b1111 8
b1000100010010001001000100000000001011101 9
1*
#416000000
0*
#417000000
b1 7
b10000 8
b1000100100010010001000000000010111011 9
1*
#418000000
b11101110 ,
b11101110 @
0*
#419000000
b10 7
b10001 8
b10001001000100100010000000000101110111 9
1*
#420000000
0*
#421000000
b0 7
b10010 8
b100010010001001000100000000001011101111 9
1*
#422000000
0*
#423000000
b1 7
b10011 8
b1000100100010010001000000000010111011111 9
1*
#424000000
0+
0*
#425000000
b10 7
b10100 8
b1001000100100010000000000101110111110 9
1*
#426000000
1+
0*
#427000000
b0 7
b10101 8
b10010001001000100000000001011101111101 9
1*
#428000000
0*
#429000000
b10110 8
b100100010010001000000000010111011111011 9
1*
#430000000
0*
#431000000
b1 7
b10111 8
b1001000100100010000000000101110111110111 9
1*
#432000000
0+
0*
#433000000
b10 7
b11000 8
b10001001000100000000001011101111101110 9
1*
#434000000
1+
b11001100 ,
b11001100 @
0*
#435000000
b0 7
b11001 8
b100010010001000000000010111011111011101 9
1*
#436000000
0*
#437000000
b1 7
b11010 8
b1000100100010000000000101110111110111011 9
1*
#438000000
0+
0*
#439000000
b10 7
b11011 8
b1001000100000000001011101111101110110 9
1*
#440000000
0*
#441000000
b0 7
b11100 8
b10010001000000000010111011111011101100 9
1*
#442000000
1+
0*
#443000000
b11101 8
b100100010000000000101110111110111011001 9
1*
#444000000
0*
#445000000
b1 7
b11110 8
b1001000100000000001011101111101110110011 9
1*
#446000000
0+
0*
#447000000
b10 7
b11111 8
b10001000000000010111011111011101100110 9
1*
#448000000
0*
#449000000
b0 7
b100000 8
b100010000000000101110111110111011001100 9
1*
#450000000
1+
b10101010 ,
b10101010 @
0*
#451000000
b100001 8
b1000100000000001011101111101110110011001 9
1*
#452000000
0+
0*
#453000000
b100010 8
b1000000000010111011111011101100110010 9
1*
#454000000
1+
0*
#455000000
b100011 8
b10000000000101110111110111011001100101 9
1*
#456000000
0+
0*
#457000000
b100100 8
b100000000001011101111101110110011001010 9
1*
#458000000
1+
0*
